{
	"partitions" : [
		{
			"name" : "Top",
			"pins" : [
				{
					"name" : "ETH_TX_EN",
					"strict" : false
				},
				{
					"name" : "ETH_TX_DATA[0]",
					"strict" : false
				},
				{
					"name" : "ETH_TX_DATA[1]",
					"strict" : false
				},
				{
					"name" : "ETH_TX_DATA[2]",
					"strict" : false
				},
				{
					"name" : "ETH_TX_DATA[3]",
					"strict" : false
				},
				{
					"name" : "ETH_RST_N",
					"strict" : false
				},
				{
					"name" : "rst",
					"strict" : false
				},
				{
					"name" : "ETH_TX_CLK",
					"strict" : false
				},
				{
					"name" : "clk",
					"strict" : false
				}
			]
		}
	]
}